mlx3d/__init__.py
mlx3d/cameras/__init__.py
mlx3d/io/__init__.py
mlx3d/losses/__init__.py
mlx3d/renderer/__init__.py
mlx3d/renderer/hello.py
mlx3d/structures/__init__.py
mlx3d/structures/meshes.py
mlx3d/utils/__init__.py
mlx3d/utils/array_utils.py
mlx3d-0.0.1.dist-info/LICENSE
mlx3d-0.0.1.dist-info/METADATA
mlx3d-0.0.1.dist-info/WHEEL
mlx3d-0.0.1.dist-info/entry_points.txt
mlx3d-0.0.1.dist-info/RECORD
